{
  "lastHeartbeat": 1776791000,
  "timestamp": "2026-04-21T16:58 UTC",
  "harness": "Harness 1 (Nanachi/OpenClaw)",
  "factoryStatus": {
    "ceo": "Active",
    "cto": "Available (sub-agent)",
    "cmo": "Available (sub-agent)"
  },
  "crons": {
    "CEO Daily Status Report": {
      "nextRun": "09:00 UTC daily",
      "status": "active"
    },
    "CEO Self-Reflection": {
      "nextRun": "every 4h",
      "status": "active"
    },
    "Memory Dreaming Promotion": {
      "nextRun": "03:00 UTC daily",
      "status": "active"
    }
  },
  "db": {
    "projects": 25,
    "channels": 8,
    "agents": 4
  },
  "bitwarden": {
    "total_items": 19,
    "categories": {
      "API Keys": 7,
      "Other": 8,
      "AI Services": 2,
      "Git/Code": 2
    }
  },
  "coolify": {
    "total_apps": 30,
    "deleted_today": [
      "AIO Sandbox",
      "deer-flow-builder",
      "factory-discord"
    ],
    "unhealthy": [
      "Temporal",
      "factory-v2",
      "novu"
    ]
  },
  "projects": {
    "launch": 5,
    "mvp": 3,
    "idea": 17,
    "launch_mrr": "$0",
    "concerns": [
      "Self-Degree Framework: Stage=MVP but Status=Launched",
      "Project [51]: name=None (data issue)",
      "All projects: $0 MRR, 0 users"
    ]
  },
  "pendingTasks": [
    "Hermes CEO (Nezuko) \u2014 needs daily report cron in hermes-agent-deploy",
    "Rick (Harness 3) \u2014 not deployed",
    "mem0 \u2014 self-hosted, not configured across harnesses",
    "Clean up unhealthy Coolify apps: Temporal, factory-v2, novu (need confirmation)"
  ],
  "blockers": []
}